qnapstats/__init__.py
qnapstats/qnap_stats.py
qnapstats-0.4.0.dist-info/LICENSE
qnapstats-0.4.0.dist-info/METADATA
qnapstats-0.4.0.dist-info/WHEEL
qnapstats-0.4.0.dist-info/top_level.txt
qnapstats-0.4.0.dist-info/RECORD
