Metadata-Version: 2.1
Name: qnapstats
Version: 0.4.0
Summary: Python API for obtaining QNAP NAS system stats
Home-page: https://github.com/colinodell/python-qnapstats
Author: Colin O'Dell
Author-email: colinodell@gmail.com
License: MIT
Keywords: qnap
Platform: UNKNOWN
Classifier: Intended Audience :: Developers
Classifier: Intended Audience :: System Administrators
Classifier: License :: OSI Approved :: MIT License
Classifier: Operating System :: OS Independent
Classifier: Programming Language :: Python :: 3
Classifier: Programming Language :: Python :: 3.5
Classifier: Programming Language :: Python :: 3.6
Classifier: Programming Language :: Python :: 3.7
Classifier: Programming Language :: Python :: 3.8
Classifier: Programming Language :: Python :: 3.9
Classifier: Topic :: Home Automation
Classifier: Topic :: System :: Monitoring
License-File: LICENSE
